drf_values_viewset/__init__.py
drf_values_viewset-0.1.0.dist-info/LICENSE
drf_values_viewset-0.1.0.dist-info/METADATA
drf_values_viewset-0.1.0.dist-info/WHEEL
drf_values_viewset-0.1.0.dist-info/top_level.txt
drf_values_viewset-0.1.0.dist-info/RECORD
