Metadata-Version: 2.1
Name: drf-values-viewset
Version: 0.1.0
Summary: A Viewset and Mixins for Django Rest Framework that attempts to prevent the N+1 query problem
Home-page: https://github.com/learningequality/drf-values-viewset
Author: Learning Equality
License: UNKNOWN
Platform: UNKNOWN
Requires-Dist: djangorestframework
